goidalib/__init__.py
goidalib/api_client.py
goidalib/api/ai/api.py
goidalib/api/auth/api.py
goidalib/api/checker/api.py
goidalib/api/logger/api.py
goidalib/api/modules/api.py
goidalib/api/repos/api.py
goidalib/api/service/api.py
goidalib-0.2.2.0.dist-info/METADATA
goidalib-0.2.2.0.dist-info/WHEEL
goidalib-0.2.2.0.dist-info/top_level.txt
goidalib-0.2.2.0.dist-info/RECORD
