Metadata-Version: 2.4
Name: goidalib
Version: 0.2.2.0
Summary: Library for GoidaHeta
Keywords: goidaheta,async,api,wrapper
Classifier: Programming Language :: Python :: 3.10
Classifier: Programming Language :: Python :: 3.11
Classifier: Programming Language :: Python :: 3.12
Classifier: License :: OSI Approved :: MIT License
Classifier: Operating System :: OS Independent
Classifier: Topic :: Software Development :: Libraries :: Python Modules
Requires-Python: >=3.10
Requires-Dist: aiohttp>=3.9.0
Requires-Dist: toml-cli>=0.7.0
